cltranscriptor/__init__.py
cltranscriptor/cltranscriptor.py
CLTranscriptor-0.0.6.dist-info/LICENSE
CLTranscriptor-0.0.6.dist-info/METADATA
CLTranscriptor-0.0.6.dist-info/WHEEL
CLTranscriptor-0.0.6.dist-info/top_level.txt
CLTranscriptor-0.0.6.dist-info/RECORD
