Metadata-Version: 2.1
Name: CLTranscriptor
Version: 0.0.6
Summary: Wav2Vec2-based transcriptor fine tuned on chilean lessons
Home-page: https://github.com/dannersm/CLTranscriptor
Author: Danner Schlotterbeck Mendez
Author-email: danner.schmen@ciae.uchile.cl
License: UNKNOWN
Project-URL: Bug Tracker, https://github.com/dannersm/CLTranscriptor/issues
Platform: UNKNOWN
Classifier: Programming Language :: Python :: 3
Classifier: License :: OSI Approved :: MIT License
Classifier: Operating System :: OS Independent
Requires-Python: >=3.6
License-File: LICENSE
Requires-Dist: librosa
Requires-Dist: numpy
Requires-Dist: transformers
Requires-Dist: torch
Requires-Dist: pyspellchecker
Requires-Dist: tqdm
